{
  "project_info": {
    "project_number": "694677019180",
    "project_id": "lastmile-1357"
  },
  "client": [
    {
      "client_info": {
        "mobilesdk_app_id": "1:694677019180:android:74dfc75e04baa2b9",
        "android_client_info": {
          "package_name": "com.ionicframework.starterfirebasepackv2396207"
        }
      },
      "oauth_client": [
        {
          "client_id": "694677019180-mstq7k2muik2t7g4i4e6req6caa2r68t.apps.googleusercontent.com",
          "client_type": 1,
          "android_info": {
            "package_name": "com.ionicframework.starterfirebasepackv2396207",
            "certificate_hash": "0E13A1391F5CCECCF856F185B5B178549E67E129"
          }
        },
        {
          "client_id": "694677019180-6i2fs1utnp7rvetov2ut11kqbbhbgolp.apps.googleusercontent.com",
          "client_type": 3
        }
      ],
      "api_key": [
        {
          "current_key": "AIzaSyCWWpp4PtRxt4IBp5hjoLvgl7M_XnECoLs"
        }
      ],
      "services": {
        "analytics_service": {
          "status": 1
        },
        "appinvite_service": {
          "status": 1,
          "other_platform_oauth_client": []
        },
        "ads_service": {
          "status": 1
        }
      }
    }
  ],
  "configuration_version": "1"
}